tknav/__init__.py
tknav/nav.py
tknav-1.0.dist-info/LICENSE
tknav-1.0.dist-info/METADATA
tknav-1.0.dist-info/WHEEL
tknav-1.0.dist-info/top_level.txt
tknav-1.0.dist-info/RECORD
