Metadata-Version: 2.1
Name: tknav
Version: 1.0
Summary: Simple navigation API for tkinter
Home-page: https://www.github.com/AzracStudios/tknav
Download-URL: https://github.com/AzracStudios/tknav/releases/download/release/tknav-0.1.0.tar.gz
Author: Adarsh Ravikumar
Author-email: azracstudios@gmail.com
Keywords: tkinter,nav,navigation,tknav
License-File: LICENSE
